[{"caller":"0xba826fec90cefdf6706858e5fbafcb27a290fbe0","gas_limit":152237,"gas_price":"0xc2166e900","transact_to":"0xfa1a856cfa3409cfa145fa4e20eb270df3eb21ab","value":"0x0","data":"0xa9059cbb0000000000000000000000002a35e40ee96a13185d5783ea65c82b2125594b4e000000000000000000000000000000000000000000002b016d5671ffc9b9d400","nonce":45128,"chain_id":1,"access_list":[],"gas_priority_fee":null,"blob_hashes":[],"max_fee_per_blob_gas":null,"authorization_list":null},{"caller":"0xd24400ae8bfebb18ca49be86258a3c749cf46853","gas_limit":90000,"gas_price":"0x51f4d5c00","transact_to":"0x2b7e7119b144a2532f413a1741082612820ef832","value":"0x2adc165547af000","data":"0x","nonce":470034,"chain_id":null,"access_list":[],"gas_priority_fee":null,"blob_hashes":[],"max_fee_per_blob_gas":null,"authorization_list":null},{"caller":"0x76ce85596c2d0ad72c303bf3d7a6b1f90b32ad78","gas_limit":42000,"gas_price":"0x4a817c800","transact_to":"0x3f5ce5fbfe3e9af3971dd833d26ba9b5c936f0be","value":"0x11f745a6a9534000","data":"0x","nonce":2,"chain_id":1,"access_list":[],"gas_priority_fee":null,"blob_hashes":[],"max_fee_per_blob_gas":null,"authorization_list":null},{"caller":"0x143d0ec36bed705663f6cfe7c43aec2a5e5bcb5a","gas_limit":42000,"gas_price":"0x4a817c800","transact_to":"0x3f5ce5fbfe3e9af3971dd833d26ba9b5c936f0be","value":"0x92684f636e9e5fd","data":"0x","nonce":0,"chain_id":1,"access_list":[],"gas_priority_fee":null,"blob_hashes":[],"max_fee_per_blob_gas":null,"authorization_list":null},{"caller":"0x27fc3f0570d505a306abe01ee42bf1b740943e0e","gas_limit":42000,"gas_price":"0x4a817c800","transact_to":"0x3f5ce5fbfe3e9af3971dd833d26ba9b5c936f0be","value":"0x417a42cac430211","data":"0x","nonce":4,"chain_id":1,"access_list":[],"gas_priority_fee":null,"blob_hashes":[],"max_fee_per_blob_gas":null,"authorization_list":null},{"caller":"0x43b28715a5909d183e680ff2ce402f3cfe3a7c7b","gas_limit":42000,"gas_price":"0x4a817c800","transact_to":"0x3f5ce5fbfe3e9af3971dd833d26ba9b5c936f0be","value":"0x404e8b4bbbc6e00","data":"0x","nonce":19,"chain_id":1,"access_list":[],"gas_priority_fee":null,"blob_hashes":[],"max_fee_per_blob_gas":null,"authorization_list":null},{"caller":"0x9a69add997f0308562a40efc9356d6b197e17445","gas_limit":42000,"gas_price":"0x4a817c800","transact_to":"0x3f5ce5fbfe3e9af3971dd833d26ba9b5c936f0be","value":"0x2c82ffdcb892950","data":"0x","nonce":184,"chain_id":1,"access_list":[],"gas_priority_fee":null,"blob_hashes":[],"max_fee_per_blob_gas":null,"authorization_list":null},{"caller":"0x05dc090038eb6eae4806887cb76a3ad87ef54630","gas_limit":42000,"gas_price":"0x4a817c800","transact_to":"0x3f5ce5fbfe3e9af3971dd833d26ba9b5c936f0be","value":"0x14cf94109c47c000","data":"0x","nonce":14,"chain_id":1,"access_list":[],"gas_priority_fee":null,"blob_hashes":[],"max_fee_per_blob_gas":null,"authorization_list":null},{"caller":"0x6ad4dab77351ec62bc16de1bc5f26a3da71e6d69","gas_limit":42000,"gas_price":"0x4a817c800","transact_to":"0x3f5ce5fbfe3e9af3971dd833d26ba9b5c936f0be","value":"0x35e760fc36ef000","data":"0x","nonce":9,"chain_id":1,"access_list":[],"gas_priority_fee":null,"blob_hashes":[],"max_fee_per_blob_gas":null,"authorization_list":null},{"caller":"0x3436c62ad69361566de8b9089454d66d028b17bb","gas_limit":42000,"gas_price":"0x4a817c800","transact_to":"0x3f5ce5fbfe3e9af3971dd833d26ba9b5c936f0be","value":"0x36e5f6f0614f000","data":"0x","nonce":35,"chain_id":1,"access_list":[],"gas_priority_fee":null,"blob_hashes":[],"max_fee_per_blob_gas":null,"authorization_list":null},{"caller":"0xbdd549f3a94c3271b9dad9fc9da3ce1a5d79df9f","gas_limit":42000,"gas_price":"0x4a817c800","transact_to":"0x3f5ce5fbfe3e9af3971dd833d26ba9b5c936f0be","value":"0x2c99483443edc78","data":"0x","nonce":26,"chain_id":1,"access_list":[],"gas_priority_fee":null,"blob_hashes":[],"max_fee_per_blob_gas":null,"authorization_list":null},{"caller":"0x927366f48ffc21081751dd02b1c6da86cabd41bb","gas_limit":42000,"gas_price":"0x4a817c800","transact_to":"0x3f5ce5fbfe3e9af3971dd833d26ba9b5c936f0be","value":"0xc1321e98da2f000","data":"0x","nonce":19,"chain_id":1,"access_list":[],"gas_priority_fee":null,"blob_hashes":[],"max_fee_per_blob_gas":null,"authorization_list":null},{"caller":"0xa37ab1d1ab48be95afa405d0908d67de31af76db","gas_limit":42000,"gas_price":"0x4a817c800","transact_to":"0x3f5ce5fbfe3e9af3971dd833d26ba9b5c936f0be","value":"0xeee81babba24000","data":"0x","nonce":6,"chain_id":1,"access_list":[],"gas_priority_fee":null,"blob_hashes":[],"max_fee_per_blob_gas":null,"authorization_list":null},{"caller":"0x65b78918bb0ab2a8894b8a757175de08900460e6","gas_limit":42000,"gas_price":"0x4a817c800","transact_to":"0x3f5ce5fbfe3e9af3971dd833d26ba9b5c936f0be","value":"0x2c57a7781fd5d56","data":"0x","nonce":14,"chain_id":1,"access_list":[],"gas_priority_fee":null,"blob_hashes":[],"max_fee_per_blob_gas":null,"authorization_list":null},{"caller":"0x06136f203bcf65c9ace50df5e47abadf1749e0c2","gas_limit":85000,"gas_price":"0x5ff6a680","transact_to":"0x4cc29dd2b01a3e0ed005c6e2deb5b3666e4c240c","value":"0x0","data":"0x","nonce":28,"chain_id":null,"access_list":[],"gas_priority_fee":null,"blob_hashes":[],"max_fee_per_blob_gas":null,"authorization_list":null},{"caller":"0x0cd3792b6113d44304e91a72021916d364331617","gas_limit":100000,"gas_price":"0x5ff6a680","transact_to":"0x4cc29dd2b01a3e0ed005c6e2deb5b3666e4c240c","value":"0x0","data":"0x","nonce":15,"chain_id":null,"access_list":[],"gas_priority_fee":null,"blob_hashes":[],"max_fee_per_blob_gas":null,"authorization_list":null},{"caller":"0xe9b6822770893579edd244bd68c4e61ddfdab114","gas_limit":100000,"gas_price":"0x5ff6a680","transact_to":"0x4cc29dd2b01a3e0ed005c6e2deb5b3666e4c240c","value":"0x0","data":"0x","nonce":14,"chain_id":null,"access_list":[],"gas_priority_fee":null,"blob_hashes":[],"max_fee_per_blob_gas":null,"authorization_list":null},{"caller":"0x82c01bc87b92316dc80975a9968ae04f672098eb","gas_limit":85000,"gas_price":"0x5ff6a680","transact_to":"0x4cc29dd2b01a3e0ed005c6e2deb5b3666e4c240c","value":"0x0","data":"0x","nonce":10,"chain_id":null,"access_list":[],"gas_priority_fee":null,"blob_hashes":[],"max_fee_per_blob_gas":null,"authorization_list":null},{"caller":"0xe8c949ee74a29f809708805fb9c97344ee80a9dc","gas_limit":100000,"gas_price":"0x5ff6a680","transact_to":"0x4cc29dd2b01a3e0ed005c6e2deb5b3666e4c240c","value":"0x0","data":"0x","nonce":14,"chain_id":null,"access_list":[],"gas_priority_fee":null,"blob_hashes":[],"max_fee_per_blob_gas":null,"authorization_list":null},{"caller":"0x21f9ffef0db2fabedd1fd9c71490e5332b6713cf","gas_limit":85000,"gas_price":"0x5ff6a680","transact_to":"0x4cc29dd2b01a3e0ed005c6e2deb5b3666e4c240c","value":"0x0","data":"0x","nonce":23,"chain_id":null,"access_list":[],"gas_priority_fee":null,"blob_hashes":[],"max_fee_per_blob_gas":null,"authorization_list":null},{"caller":"0x39c77c18366d95752f2b9fefb6039b9748ea2dd2","gas_limit":85000,"gas_price":"0x5ff6a680","transact_to":"0x4cc29dd2b01a3e0ed005c6e2deb5b3666e4c240c","value":"0x0","data":"0x","nonce":22,"chain_id":null,"access_list":[],"gas_priority_fee":null,"blob_hashes":[],"max_fee_per_blob_gas":null,"authorization_list":null},{"caller":"0xd447bd4494ef5fb63bb37cee290138690b69f3c6","gas_limit":100000,"gas_price":"0x5ff6a680","transact_to":"0x4cc29dd2b01a3e0ed005c6e2deb5b3666e4c240c","value":"0x0","data":"0x","nonce":14,"chain_id":null,"access_list":[],"gas_priority_fee":null,"blob_hashes":[],"max_fee_per_blob_gas":null,"authorization_list":null},{"caller":"0xde3c072877302c76af7be767848b4e1308730655","gas_limit":100000,"gas_price":"0x5ff6a680","transact_to":"0x4cc29dd2b01a3e0ed005c6e2deb5b3666e4c240c","value":"0x0","data":"0x","nonce":14,"chain_id":null,"access_list":[],"gas_priority_fee":null,"blob_hashes":[],"max_fee_per_blob_gas":null,"authorization_list":null},{"caller":"0x967ca3c711e21a727652bc533860a6a347f0801a","gas_limit":85000,"gas_price":"0x5ff6a680","transact_to":"0x4cc29dd2b01a3e0ed005c6e2deb5b3666e4c240c","value":"0x0","data":"0x","nonce":10,"chain_id":null,"access_list":[],"gas_priority_fee":null,"blob_hashes":[],"max_fee_per_blob_gas":null,"authorization_list":null},{"caller":"0xe89568a7bd855548b76bdb4a4b9e5747886befdf","gas_limit":100000,"gas_price":"0x5ff6a680","transact_to":"0x4cc29dd2b01a3e0ed005c6e2deb5b3666e4c240c","value":"0x0","data":"0x","nonce":14,"chain_id":null,"access_list":[],"gas_priority_fee":null,"blob_hashes":[],"max_fee_per_blob_gas":null,"authorization_list":null},{"caller":"0xc0690e5470695d1f76701efb435ed29cf2ac8985","gas_limit":100000,"gas_price":"0x5ff6a680","transact_to":"0x4cc29dd2b01a3e0ed005c6e2deb5b3666e4c240c","value":"0x0","data":"0x","nonce":14,"chain_id":null,"access_list":[],"gas_priority_fee":null,"blob_hashes":[],"max_fee_per_blob_gas":null,"authorization_list":null},{"caller":"0x81922bd55e8e925cc82ebe9b337326e176c29d72","gas_limit":85000,"gas_price":"0x5ff6a680","transact_to":"0x4cc29dd2b01a3e0ed005c6e2deb5b3666e4c240c","value":"0x0","data":"0x","nonce":10,"chain_id":null,"access_list":[],"gas_priority_fee":null,"blob_hashes":[],"max_fee_per_blob_gas":null,"authorization_list":null},{"caller":"0xad9cabba08237265b811740d8654530c5f62c2a4","gas_limit":85000,"gas_price":"0x5ff6a680","transact_to":"0x4cc29dd2b01a3e0ed005c6e2deb5b3666e4c240c","value":"0x0","data":"0x","nonce":11,"chain_id":null,"access_list":[],"gas_priority_fee":null,"blob_hashes":[],"max_fee_per_blob_gas":null,"authorization_list":null},{"caller":"0xd72cecf260a84291184c4d43ec98ab006a237ebe","gas_limit":100000,"gas_price":"0x5ff6a680","transact_to":"0x4cc29dd2b01a3e0ed005c6e2deb5b3666e4c240c","value":"0x0","data":"0x","nonce":14,"chain_id":null,"access_list":[],"gas_priority_fee":null,"blob_hashes":[],"max_fee_per_blob_gas":null,"authorization_list":null},{"caller":"0xda52ea1bb532153fc680418b4cad822e8ff2b7a4","gas_limit":100000,"gas_price":"0x5ff6a680","transact_to":"0x4cc29dd2b01a3e0ed005c6e2deb5b3666e4c240c","value":"0x0","data":"0x","nonce":14,"chain_id":null,"access_list":[],"gas_priority_fee":null,"blob_hashes":[],"max_fee_per_blob_gas":null,"authorization_list":null},{"caller":"0x8f0765f2b1bb34b0362c907d71c7000afa2eab9d","gas_limit":85000,"gas_price":"0x5ff6a680","transact_to":"0x4cc29dd2b01a3e0ed005c6e2deb5b3666e4c240c","value":"0x0","data":"0x","nonce":16,"chain_id":null,"access_list":[],"gas_priority_fee":null,"blob_hashes":[],"max_fee_per_blob_gas":null,"authorization_list":null},{"caller":"0x7f887caf428fc86dab3ab99e77c823861ad5ad28","gas_limit":85000,"gas_price":"0x5ff6a680","transact_to":"0x4cc29dd2b01a3e0ed005c6e2deb5b3666e4c240c","value":"0x0","data":"0x","nonce":16,"chain_id":null,"access_list":[],"gas_priority_fee":null,"blob_hashes":[],"max_fee_per_blob_gas":null,"authorization_list":null},{"caller":"0xea99b37a42c3351c8ed9e44bd3baa478b25c74c6","gas_limit":100000,"gas_price":"0x5ff6a680","transact_to":"0x4cc29dd2b01a3e0ed005c6e2deb5b3666e4c240c","value":"0x0","data":"0x","nonce":14,"chain_id":null,"access_list":[],"gas_priority_fee":null,"blob_hashes":[],"max_fee_per_blob_gas":null,"authorization_list":null},{"caller":"0xcff5673f64ca06311490a95557d6884bcdb1deb0","gas_limit":100000,"gas_price":"0x5ff6a680","transact_to":"0x4cc29dd2b01a3e0ed005c6e2deb5b3666e4c240c","value":"0x0","data":"0x","nonce":14,"chain_id":null,"access_list":[],"gas_priority_fee":null,"blob_hashes":[],"max_fee_per_blob_gas":null,"authorization_list":null},{"caller":"0xc3fb102fc63657253f02d1271a713411fe981fd9","gas_limit":100000,"gas_price":"0x5ff6a680","transact_to":"0x4cc29dd2b01a3e0ed005c6e2deb5b3666e4c240c","value":"0x0","data":"0x","nonce":14,"chain_id":null,"access_list":[],"gas_priority_fee":null,"blob_hashes":[],"max_fee_per_blob_gas":null,"authorization_list":null},{"caller":"0xccb6bac8955bb34ae33cb31149725d981390c964","gas_limit":100000,"gas_price":"0x5ff6a680","transact_to":"0x4cc29dd2b01a3e0ed005c6e2deb5b3666e4c240c","value":"0x0","data":"0x","nonce":14,"chain_id":null,"access_list":[],"gas_priority_fee":null,"blob_hashes":[],"max_fee_per_blob_gas":null,"authorization_list":null},{"caller":"0x0dd9ce57f2a4a01e78262f48361dd19dd9eaf034","gas_limit":100000,"gas_price":"0x5ff6a680","transact_to":"0x4cc29dd2b01a3e0ed005c6e2deb5b3666e4c240c","value":"0x0","data":"0x","nonce":15,"chain_id":null,"access_list":[],"gas_priority_fee":null,"blob_hashes":[],"max_fee_per_blob_gas":null,"authorization_list":null},{"caller":"0x23697a6944c586d88e0ed047ed24a29f25d860d2","gas_limit":85000,"gas_price":"0x5ff6a680","transact_to":"0x4cc29dd2b01a3e0ed005c6e2deb5b3666e4c240c","value":"0x0","data":"0x","nonce":24,"chain_id":null,"access_list":[],"gas_priority_fee":null,"blob_hashes":[],"max_fee_per_blob_gas":null,"authorization_list":null},{"caller":"0xf8ddf98285e4e84c34fd30a2c03c4a08dbb07e08","gas_limit":100000,"gas_price":"0x5ff6a680","transact_to":"0x4cc29dd2b01a3e0ed005c6e2deb5b3666e4c240c","value":"0x0","data":"0x","nonce":14,"chain_id":null,"access_list":[],"gas_priority_fee":null,"blob_hashes":[],"max_fee_per_blob_gas":null,"authorization_list":null},{"caller":"0xcef07846bbcf461c7b25f4d981e8936738d316de","gas_limit":85000,"gas_price":"0x5ff6a680","transact_to":"0x4cc29dd2b01a3e0ed005c6e2deb5b3666e4c240c","value":"0x0","data":"0x","nonce":10,"chain_id":null,"access_list":[],"gas_priority_fee":null,"blob_hashes":[],"max_fee_per_blob_gas":null,"authorization_list":null},{"caller":"0x7790c3d035c2823568a376a966151e88bd199193","gas_limit":85000,"gas_price":"0x5ff6a680","transact_to":"0x4cc29dd2b01a3e0ed005c6e2deb5b3666e4c240c","value":"0x0","data":"0x","nonce":18,"chain_id":null,"access_list":[],"gas_priority_fee":null,"blob_hashes":[],"max_fee_per_blob_gas":null,"authorization_list":null},{"caller":"0xd9004c62778e6a17a159f2c6684cb4d643122118","gas_limit":100000,"gas_price":"0x5ff6a680","transact_to":"0x4cc29dd2b01a3e0ed005c6e2deb5b3666e4c240c","value":"0x0","data":"0x","nonce":14,"chain_id":null,"access_list":[],"gas_priority_fee":null,"blob_hashes":[],"max_fee_per_blob_gas":null,"authorization_list":null},{"caller":"0xdeeb184e697d8880b0cf4b3207d160a59573ca47","gas_limit":100000,"gas_price":"0x5ff6a680","transact_to":"0x4cc29dd2b01a3e0ed005c6e2deb5b3666e4c240c","value":"0x0","data":"0x","nonce":14,"chain_id":null,"access_list":[],"gas_priority_fee":null,"blob_hashes":[],"max_fee_per_blob_gas":null,"authorization_list":null},{"caller":"0x9e9171b1bf6aceb141070f6eb08a48052e296651","gas_limit":85000,"gas_price":"0x5ff6a680","transact_to":"0x4cc29dd2b01a3e0ed005c6e2deb5b3666e4c240c","value":"0x0","data":"0x","nonce":17,"chain_id":null,"access_list":[],"gas_priority_fee":null,"blob_hashes":[],"max_fee_per_blob_gas":null,"authorization_list":null},{"caller":"0xe818facd1d5589fcd080165447e7a0eff7427b65","gas_limit":100000,"gas_price":"0x5ff6a680","transact_to":"0x4cc29dd2b01a3e0ed005c6e2deb5b3666e4c240c","value":"0x0","data":"0x","nonce":14,"chain_id":null,"access_list":[],"gas_priority_fee":null,"blob_hashes":[],"max_fee_per_blob_gas":null,"authorization_list":null},{"caller":"0x368fb48be289bd84f235c3bac3286faea76eae8a","gas_limit":100000,"gas_price":"0x5ff6a680","transact_to":"0x4cc29dd2b01a3e0ed005c6e2deb5b3666e4c240c","value":"0x0","data":"0x","nonce":8,"chain_id":null,"access_list":[],"gas_priority_fee":null,"blob_hashes":[],"max_fee_per_blob_gas":null,"authorization_list":null},{"caller":"0xc41e22d47615ea58a6b824eb3710ce32dbe451c6","gas_limit":100000,"gas_price":"0x5ff6a680","transact_to":"0x4cc29dd2b01a3e0ed005c6e2deb5b3666e4c240c","value":"0x0","data":"0x","nonce":14,"chain_id":null,"access_list":[],"gas_priority_fee":null,"blob_hashes":[],"max_fee_per_blob_gas":null,"authorization_list":null},{"caller":"0xef672789be4010e0ecbffb0b87b72551d5099ac1","gas_limit":100000,"gas_price":"0x5ff6a680","transact_to":"0x4cc29dd2b01a3e0ed005c6e2deb5b3666e4c240c","value":"0x0","data":"0x","nonce":14,"chain_id":null,"access_list":[],"gas_priority_fee":null,"blob_hashes":[],"max_fee_per_blob_gas":null,"authorization_list":null},{"caller":"0xe0f26089f840abcbe1d9b49ca6c1a431e42c7079","gas_limit":100000,"gas_price":"0x5ff6a680","transact_to":"0x4cc29dd2b01a3e0ed005c6e2deb5b3666e4c240c","value":"0x0","data":"0x","nonce":14,"chain_id":null,"access_list":[],"gas_priority_fee":null,"blob_hashes":[],"max_fee_per_blob_gas":null,"authorization_list":null},{"caller":"0x28a9eafdd1babf08038e5da974d168d8f7942749","gas_limit":85000,"gas_price":"0x5ff6a680","transact_to":"0x4cc29dd2b01a3e0ed005c6e2deb5b3666e4c240c","value":"0x0","data":"0x","nonce":19,"chain_id":null,"access_list":[],"gas_priority_fee":null,"blob_hashes":[],"max_fee_per_blob_gas":null,"authorization_list":null},{"caller":"0x2754443c727c3582fef8baa1e92904a2cac9f91a","gas_limit":85000,"gas_price":"0x5ff6a680","transact_to":"0x4cc29dd2b01a3e0ed005c6e2deb5b3666e4c240c","value":"0x0","data":"0x","nonce":21,"chain_id":null,"access_list":[],"gas_priority_fee":null,"blob_hashes":[],"max_fee_per_blob_gas":null,"authorization_list":null},{"caller":"0x62e74135bfe65a39a7f50e70695e413b35847827","gas_limit":85000,"gas_price":"0x5ff6a680","transact_to":"0x4cc29dd2b01a3e0ed005c6e2deb5b3666e4c240c","value":"0x0","data":"0x","nonce":12,"chain_id":null,"access_list":[],"gas_priority_fee":null,"blob_hashes":[],"max_fee_per_blob_gas":null,"authorization_list":null},{"caller":"0xe5aa5f575a68ec4407b568a4fc331b07ae070ae1","gas_limit":100000,"gas_price":"0x5ff6a680","transact_to":"0x4cc29dd2b01a3e0ed005c6e2deb5b3666e4c240c","value":"0x0","data":"0x","nonce":14,"chain_id":null,"access_list":[],"gas_priority_fee":null,"blob_hashes":[],"max_fee_per_blob_gas":null,"authorization_list":null},{"caller":"0xf4d82f0d5c0f1c40c303ea75063865a6a075421e","gas_limit":100000,"gas_price":"0x5ff6a680","transact_to":"0x4cc29dd2b01a3e0ed005c6e2deb5b3666e4c240c","value":"0x0","data":"0x","nonce":14,"chain_id":null,"access_list":[],"gas_priority_fee":null,"blob_hashes":[],"max_fee_per_blob_gas":null,"authorization_list":null},{"caller":"0xfec63a50cfa0126305bd366b6796e0d2b69d80bf","gas_limit":100000,"gas_price":"0x5ff6a680","transact_to":"0x4cc29dd2b01a3e0ed005c6e2deb5b3666e4c240c","value":"0x0","data":"0x","nonce":14,"chain_id":null,"access_list":[],"gas_priority_fee":null,"blob_hashes":[],"max_fee_per_blob_gas":null,"authorization_list":null},{"caller":"0xcf6bd3d37273ffe8dab03a9c595425fba5aee626","gas_limit":100000,"gas_price":"0x5ff6a680","transact_to":"0x4cc29dd2b01a3e0ed005c6e2deb5b3666e4c240c","value":"0x0","data":"0x","nonce":14,"chain_id":null,"access_list":[],"gas_priority_fee":null,"blob_hashes":[],"max_fee_per_blob_gas":null,"authorization_list":null},{"caller":"0xdd7af0717f24c85eeb862974151c0fe030399a60","gas_limit":100000,"gas_price":"0x5ff6a680","transact_to":"0x4cc29dd2b01a3e0ed005c6e2deb5b3666e4c240c","value":"0x0","data":"0x","nonce":14,"chain_id":null,"access_list":[],"gas_priority_fee":null,"blob_hashes":[],"max_fee_per_blob_gas":null,"authorization_list":null},{"caller":"0x2d2ccf44793f7abb6b8faf138788ef0d7d724356","gas_limit":100000,"gas_price":"0x5ff6a680","transact_to":"0x4cc29dd2b01a3e0ed005c6e2deb5b3666e4c240c","value":"0x0","data":"0x","nonce":8,"chain_id":null,"access_list":[],"gas_priority_fee":null,"blob_hashes":[],"max_fee_per_blob_gas":null,"authorization_list":null},{"caller":"0x628b37e1c5c4685d899308e001ccf6227ad836b7","gas_limit":85000,"gas_price":"0x5ff6a680","transact_to":"0x4cc29dd2b01a3e0ed005c6e2deb5b3666e4c240c","value":"0x0","data":"0x","nonce":19,"chain_id":null,"access_list":[],"gas_priority_fee":null,"blob_hashes":[],"max_fee_per_blob_gas":null,"authorization_list":null},{"caller":"0xb6636d168e2269002de04ae51127420eec29db9f","gas_limit":100000,"gas_price":"0x5ff6a680","transact_to":"0x4cc29dd2b01a3e0ed005c6e2deb5b3666e4c240c","value":"0x0","data":"0x","nonce":15,"chain_id":null,"access_list":[],"gas_priority_fee":null,"blob_hashes":[],"max_fee_per_blob_gas":null,"authorization_list":null},{"caller":"0xd2dbac72f195eb91865647e1f483befaab8e1ba0","gas_limit":100000,"gas_price":"0x5ff6a680","transact_to":"0x4cc29dd2b01a3e0ed005c6e2deb5b3666e4c240c","value":"0x0","data":"0x","nonce":14,"chain_id":null,"access_list":[],"gas_priority_fee":null,"blob_hashes":[],"max_fee_per_blob_gas":null,"authorization_list":null},{"caller":"0x8e6074356276981ea52ef8f8b7939e8bf51afc6b","gas_limit":85000,"gas_price":"0x5ff6a680","transact_to":"0x4cc29dd2b01a3e0ed005c6e2deb5b3666e4c240c","value":"0x0","data":"0x","nonce":16,"chain_id":null,"access_list":[],"gas_priority_fee":null,"blob_hashes":[],"max_fee_per_blob_gas":null,"authorization_list":null},{"caller":"0xcc1ef1c029378605834f0c69825f0a93cf2576a6","gas_limit":100000,"gas_price":"0x5ff6a680","transact_to":"0x4cc29dd2b01a3e0ed005c6e2deb5b3666e4c240c","value":"0x0","data":"0x","nonce":14,"chain_id":null,"access_list":[],"gas_priority_fee":null,"blob_hashes":[],"max_fee_per_blob_gas":null,"authorization_list":null},{"caller":"0xf667902a0a5a67a46b8a863327ee53d2e70735ea","gas_limit":300000,"gas_price":"0x5f5e1000","transact_to":"0x73d0ed7e3ebdd0ed160a1fe5fee511943e102879","value":"0x0","data":"0x1e9a695000000000000000000000000003ebcfd76120d7c5bcb07f56e6386406af7f6dbf0000000000000000000000000000000000000000000000000000000000133eb8","nonce":237,"chain_id":null,"access_list":[],"gas_priority_fee":null,"blob_hashes":[],"max_fee_per_blob_gas":null,"authorization_list":null},{"caller":"0x03e78f8710e5479a1f017ed4c8c9387bc80f94f8","gas_limit":100000,"gas_price":"0x5f5e1000","transact_to":"0x5fa1ea99eb3acc1f9e84cf28fde6431b8fdc9dc0","value":"0x0","data":"0x","nonce":11,"chain_id":1,"access_list":[],"gas_priority_fee":null,"blob_hashes":[],"max_fee_per_blob_gas":null,"authorization_list":null},{"caller":"0x9ba7167ae91bf1d173bcdc3835607c470c2af441","gas_limit":420000,"gas_price":"0x5f5e1000","transact_to":"0xcb47c89cb17c10b719fc5ed9665bae157cac2cb1","value":"0x0","data":"0x3ccfd60b","nonce":18,"chain_id":1,"access_list":[],"gas_priority_fee":null,"blob_hashes":[],"max_fee_per_blob_gas":null,"authorization_list":null},{"caller":"0x49bfa51840f34e7f538133d169ff79dab962c136","gas_limit":100000,"gas_price":"0x5e2ce300","transact_to":"0x2fe0bc5ffb80a84739da913f0a393a4b0cce661b","value":"0x0","data":"0x","nonce":35,"chain_id":1,"access_list":[],"gas_priority_fee":null,"blob_hashes":[],"max_fee_per_blob_gas":null,"authorization_list":null},{"caller":"0xac463c3d2c47367b14b019e3d64effd4e5ef62de","gas_limit":360000,"gas_price":"0x5b18e580","transact_to":"0xa5996f6b731b349e25d7d5f4dd93a5ce9947841f","value":"0x0","data":"0xa9059cbb000000000000000000000000c7dd594db62f5c9494082e933ee734ff6cfe8a3b00000000000000000000000000000000000000000000003635c9adc5dea00000","nonce":9,"chain_id":1,"access_list":[],"gas_priority_fee":null,"blob_hashes":[],"max_fee_per_blob_gas":null,"authorization_list":null},{"caller":"0xc0189c6087adf9f4125eb3fa86cb2d3173ff33ca","gas_limit":200000,"gas_price":"0x5a995c00","transact_to":"0x67a5de922c1f4d1a4dbd848466b86b5455fb6a3b","value":"0x14401eab384000","data":"0x454a2ab30000000000000000000000000000000000000000000000000000000000003b61","nonce":339,"chain_id":1,"access_list":[],"gas_priority_fee":null,"blob_hashes":[],"max_fee_per_blob_gas":null,"authorization_list":null},{"caller":"0x12c6e65c83b4af0fcdf464d9d0048a6a6292d415","gas_limit":100000,"gas_price":"0x5a00c580","transact_to":"0xf1def7f0e620f39531eb352fe13da6825218e7df","value":"0x0","data":"0x","nonce":1,"chain_id":null,"access_list":[],"gas_priority_fee":null,"blob_hashes":[],"max_fee_per_blob_gas":null,"authorization_list":null},{"caller":"0x67a7e39852621b880c8c9486288843ddf94719e1","gas_limit":100000,"gas_price":"0x5a00c580","transact_to":"0xf1def7f0e620f39531eb352fe13da6825218e7df","value":"0x0","data":"0x","nonce":3,"chain_id":null,"access_list":[],"gas_priority_fee":null,"blob_hashes":[],"max_fee_per_blob_gas":null,"authorization_list":null},{"caller":"0x0451355bd5b20eb65133cc21974a6d1c3cfa63b1","gas_limit":100000,"gas_price":"0x5a00c580","transact_to":"0xf1def7f0e620f39531eb352fe13da6825218e7df","value":"0x0","data":"0x","nonce":1,"chain_id":null,"access_list":[],"gas_priority_fee":null,"blob_hashes":[],"max_fee_per_blob_gas":null,"authorization_list":null},{"caller":"0x9c14350dd1e448313ca730b458ca86506ab180bd","gas_limit":100000,"gas_price":"0x5a00c580","transact_to":"0xf1def7f0e620f39531eb352fe13da6825218e7df","value":"0x0","data":"0x","nonce":1,"chain_id":null,"access_list":[],"gas_priority_fee":null,"blob_hashes":[],"max_fee_per_blob_gas":null,"authorization_list":null},{"caller":"0x76269c53c26980b55b1c6317b3993b43379032bf","gas_limit":100000,"gas_price":"0x5a00c580","transact_to":"0xf1def7f0e620f39531eb352fe13da6825218e7df","value":"0x0","data":"0x","nonce":1,"chain_id":null,"access_list":[],"gas_priority_fee":null,"blob_hashes":[],"max_fee_per_blob_gas":null,"authorization_list":null},{"caller":"0xe57cc4280b192752530a0125511787340c1284dd","gas_limit":100000,"gas_price":"0x5a00c580","transact_to":"0x0cfda67b0067f1a99deb1cb80e0273a3f26d317c","value":"0x0","data":"0x","nonce":2,"chain_id":null,"access_list":[],"gas_priority_fee":null,"blob_hashes":[],"max_fee_per_blob_gas":null,"authorization_list":null},{"caller":"0x2ec94e2026021724e6599847492e675c678ab6b7","gas_limit":100000,"gas_price":"0x5a00c580","transact_to":"0xf1def7f0e620f39531eb352fe13da6825218e7df","value":"0x0","data":"0x","nonce":1,"chain_id":null,"access_list":[],"gas_priority_fee":null,"blob_hashes":[],"max_fee_per_blob_gas":null,"authorization_list":null},{"caller":"0x640209d17628f16f6cd6e1e2c33c9d3de4d2907b","gas_limit":100000,"gas_price":"0x5a00c580","transact_to":"0xf1def7f0e620f39531eb352fe13da6825218e7df","value":"0x0","data":"0x","nonce":1,"chain_id":null,"access_list":[],"gas_priority_fee":null,"blob_hashes":[],"max_fee_per_blob_gas":null,"authorization_list":null},{"caller":"0x4e340b7a24e49138d3e1c949789d43dbf22fedd4","gas_limit":100000,"gas_price":"0x5a00c580","transact_to":"0xf1def7f0e620f39531eb352fe13da6825218e7df","value":"0x0","data":"0x","nonce":3,"chain_id":null,"access_list":[],"gas_priority_fee":null,"blob_hashes":[],"max_fee_per_blob_gas":null,"authorization_list":null},{"caller":"0x6ea723f922cc836fa452c70f19fb3396f1ea229d","gas_limit":100000,"gas_price":"0x5a00c580","transact_to":"0xf1def7f0e620f39531eb352fe13da6825218e7df","value":"0x0","data":"0x","nonce":1,"chain_id":null,"access_list":[],"gas_priority_fee":null,"blob_hashes":[],"max_fee_per_blob_gas":null,"authorization_list":null},{"caller":"0x167b27e01770fdc3813337b321aae47d46814095","gas_limit":100000,"gas_price":"0x5a00c580","transact_to":"0xf1def7f0e620f39531eb352fe13da6825218e7df","value":"0x0","data":"0x","nonce":1,"chain_id":null,"access_list":[],"gas_priority_fee":null,"blob_hashes":[],"max_fee_per_blob_gas":null,"authorization_list":null},{"caller":"0x96b430438077eed65e2dd4779ecafa6e18046513","gas_limit":100000,"gas_price":"0x5a00c580","transact_to":"0x0cfda67b0067f1a99deb1cb80e0273a3f26d317c","value":"0x0","data":"0x","nonce":2,"chain_id":null,"access_list":[],"gas_priority_fee":null,"blob_hashes":[],"max_fee_per_blob_gas":null,"authorization_list":null},{"caller":"0x578f6ee6950e65d5562b8932904b42e56fd1b638","gas_limit":100000,"gas_price":"0x5a00c580","transact_to":"0xf1def7f0e620f39531eb352fe13da6825218e7df","value":"0x0","data":"0x","nonce":3,"chain_id":null,"access_list":[],"gas_priority_fee":null,"blob_hashes":[],"max_fee_per_blob_gas":null,"authorization_list":null},{"caller":"0x0e4b55f69d182171f98882b7bc1265d786f06554","gas_limit":100000,"gas_price":"0x5a00c580","transact_to":"0x0cfda67b0067f1a99deb1cb80e0273a3f26d317c","value":"0x0","data":"0x","nonce":2,"chain_id":null,"access_list":[],"gas_priority_fee":null,"blob_hashes":[],"max_fee_per_blob_gas":null,"authorization_list":null},{"caller":"0x000650f9e1785b19f3b1d7cbcb25fd619bd6515f","gas_limit":100000,"gas_price":"0x5a00c580","transact_to":"0xf1def7f0e620f39531eb352fe13da6825218e7df","value":"0x0","data":"0x","nonce":1,"chain_id":null,"access_list":[],"gas_priority_fee":null,"blob_hashes":[],"max_fee_per_blob_gas":null,"authorization_list":null},{"caller":"0x6d62e5462733242b3336e99ee8ab66fd57e71ff2","gas_limit":100000,"gas_price":"0x5a00c580","transact_to":"0xf1def7f0e620f39531eb352fe13da6825218e7df","value":"0x0","data":"0x","nonce":3,"chain_id":null,"access_list":[],"gas_priority_fee":null,"blob_hashes":[],"max_fee_per_blob_gas":null,"authorization_list":null},{"caller":"0xe978f9069eb19bed2683f0242c1ecc1cf217d2bf","gas_limit":100000,"gas_price":"0x5a00c580","transact_to":"0x0cfda67b0067f1a99deb1cb80e0273a3f26d317c","value":"0x0","data":"0x","nonce":2,"chain_id":null,"access_list":[],"gas_priority_fee":null,"blob_hashes":[],"max_fee_per_blob_gas":null,"authorization_list":null},{"caller":"0xbc6622d51df1f9d9da92056ea68320a363915e4b","gas_limit":100000,"gas_price":"0x5a00c580","transact_to":"0xf1def7f0e620f39531eb352fe13da6825218e7df","value":"0x0","data":"0x","nonce":1,"chain_id":null,"access_list":[],"gas_priority_fee":null,"blob_hashes":[],"max_fee_per_blob_gas":null,"authorization_list":null},{"caller":"0x257c4e5e7ac12b467050ae7a1a44d87a2b1ead9b","gas_limit":100000,"gas_price":"0x5a00c580","transact_to":"0xf1def7f0e620f39531eb352fe13da6825218e7df","value":"0x0","data":"0x","nonce":1,"chain_id":null,"access_list":[],"gas_priority_fee":null,"blob_hashes":[],"max_fee_per_blob_gas":null,"authorization_list":null},{"caller":"0x1ef8d840f870f63da1cf163adc73124c8102c805","gas_limit":100000,"gas_price":"0x5a00c580","transact_to":"0x0cfda67b0067f1a99deb1cb80e0273a3f26d317c","value":"0x0","data":"0x","nonce":2,"chain_id":null,"access_list":[],"gas_priority_fee":null,"blob_hashes":[],"max_fee_per_blob_gas":null,"authorization_list":null},{"caller":"0x9de5342158e5d9bb4f209208ebd4a3b1b9d71c54","gas_limit":100000,"gas_price":"0x5a00c580","transact_to":"0xf1def7f0e620f39531eb352fe13da6825218e7df","value":"0x0","data":"0x","nonce":1,"chain_id":null,"access_list":[],"gas_priority_fee":null,"blob_hashes":[],"max_fee_per_blob_gas":null,"authorization_list":null},{"caller":"0x561b607438012f5cb29ed9c3754949706830e135","gas_limit":100000,"gas_price":"0x5a00c580","transact_to":"0xf1def7f0e620f39531eb352fe13da6825218e7df","value":"0x0","data":"0x","nonce":3,"chain_id":null,"access_list":[],"gas_priority_fee":null,"blob_hashes":[],"max_fee_per_blob_gas":null,"authorization_list":null},{"caller":"0xcb0add6051c718049fa8b37a5029aabe26cf5ba6","gas_limit":100000,"gas_price":"0x5a00c580","transact_to":"0xf1def7f0e620f39531eb352fe13da6825218e7df","value":"0x0","data":"0x","nonce":1,"chain_id":null,"access_list":[],"gas_priority_fee":null,"blob_hashes":[],"max_fee_per_blob_gas":null,"authorization_list":null},{"caller":"0x5b99f90a8385918a6880a7993de5c91e0c06b487","gas_limit":100000,"gas_price":"0x5a00c580","transact_to":"0xf1def7f0e620f39531eb352fe13da6825218e7df","value":"0x0","data":"0x","nonce":3,"chain_id":null,"access_list":[],"gas_priority_fee":null,"blob_hashes":[],"max_fee_per_blob_gas":null,"authorization_list":null},{"caller":"0xa1486e1fed3f1d13f53c0cefcce3d852b5c15fb3","gas_limit":100000,"gas_price":"0x5a00c580","transact_to":"0xf1def7f0e620f39531eb352fe13da6825218e7df","value":"0x0","data":"0x","nonce":3,"chain_id":null,"access_list":[],"gas_priority_fee":null,"blob_hashes":[],"max_fee_per_blob_gas":null,"authorization_list":null},{"caller":"0xe90ce013cf1d134924f519a3f11592f92be9202f","gas_limit":100000,"gas_price":"0x5a00c580","transact_to":"0xf1def7f0e620f39531eb352fe13da6825218e7df","value":"0x0","data":"0x","nonce":3,"chain_id":null,"access_list":[],"gas_priority_fee":null,"blob_hashes":[],"max_fee_per_blob_gas":null,"authorization_list":null},{"caller":"0x46731efd1a5abed45a5661875e26e6757619ae6c","gas_limit":100000,"gas_price":"0x5a00c580","transact_to":"0xf1def7f0e620f39531eb352fe13da6825218e7df","value":"0x0","data":"0x","nonce":1,"chain_id":null,"access_list":[],"gas_priority_fee":null,"blob_hashes":[],"max_fee_per_blob_gas":null,"authorization_list":null},{"caller":"0x7c4990cebf5e9961606092f85bc99bced2c687d2","gas_limit":100000,"gas_price":"0x5a00c580","transact_to":"0xf1def7f0e620f39531eb352fe13da6825218e7df","value":"0x0","data":"0x","nonce":1,"chain_id":null,"access_list":[],"gas_priority_fee":null,"blob_hashes":[],"max_fee_per_blob_gas":null,"authorization_list":null},{"caller":"0x30a97c39dee73c0e3d0341e8b438b37e49398fb6","gas_limit":100000,"gas_price":"0x5a00c580","transact_to":"0x0cfda67b0067f1a99deb1cb80e0273a3f26d317c","value":"0x0","data":"0x","nonce":2,"chain_id":null,"access_list":[],"gas_priority_fee":null,"blob_hashes":[],"max_fee_per_blob_gas":null,"authorization_list":null},{"caller":"0x359605b5e543bbfcbf630333f0f86473cc017ae5","gas_limit":100000,"gas_price":"0x5a00c580","transact_to":"0xf1def7f0e620f39531eb352fe13da6825218e7df","value":"0x0","data":"0x","nonce":1,"chain_id":null,"access_list":[],"gas_priority_fee":null,"blob_hashes":[],"max_fee_per_blob_gas":null,"authorization_list":null},{"caller":"0x48ed04bef9f0c5cf9a70c359e4b7bb978c62ddc5","gas_limit":100000,"gas_price":"0x5a00c580","transact_to":"0xf1def7f0e620f39531eb352fe13da6825218e7df","value":"0x0","data":"0x","nonce":1,"chain_id":null,"access_list":[],"gas_priority_fee":null,"blob_hashes":[],"max_fee_per_blob_gas":null,"authorization_list":null},{"caller":"0x65ee99b81abc79327dd23c2f34cbe7267498bba6","gas_limit":100000,"gas_price":"0x5a00c580","transact_to":"0xf1def7f0e620f39531eb352fe13da6825218e7df","value":"0x0","data":"0x","nonce":3,"chain_id":null,"access_list":[],"gas_priority_fee":null,"blob_hashes":[],"max_fee_per_blob_gas":null,"authorization_list":null},{"caller":"0x0d251142822a5c89a42b1a5d2a9a7495e5c8c77c","gas_limit":100000,"gas_price":"0x5a00c580","transact_to":"0xf1def7f0e620f39531eb352fe13da6825218e7df","value":"0x0","data":"0x","nonce":1,"chain_id":null,"access_list":[],"gas_priority_fee":null,"blob_hashes":[],"max_fee_per_blob_gas":null,"authorization_list":null},{"caller":"0x6b99fc577d9dca6e4b253822ffd30a9c1ed1dd5f","gas_limit":100000,"gas_price":"0x5a00c580","transact_to":"0x0cfda67b0067f1a99deb1cb80e0273a3f26d317c","value":"0x0","data":"0x","nonce":2,"chain_id":null,"access_list":[],"gas_priority_fee":null,"blob_hashes":[],"max_fee_per_blob_gas":null,"authorization_list":null},{"caller":"0x0fddf82b14f547542112d5eee7bb16274328b429","gas_limit":100000,"gas_price":"0x5a00c580","transact_to":"0xf1def7f0e620f39531eb352fe13da6825218e7df","value":"0x0","data":"0x","nonce":2,"chain_id":null,"access_list":[],"gas_priority_fee":null,"blob_hashes":[],"max_fee_per_blob_gas":null,"authorization_list":null},{"caller":"0x669f2167368494cc7ba7bb0ce9cb4dcec548bec5","gas_limit":100000,"gas_price":"0x5a00c580","transact_to":"0xf1def7f0e620f39531eb352fe13da6825218e7df","value":"0x0","data":"0x","nonce":1,"chain_id":null,"access_list":[],"gas_priority_fee":null,"blob_hashes":[],"max_fee_per_blob_gas":null,"authorization_list":null},{"caller":"0xe4b50b54b6fbd32a3cd11058f59da0b8962959dc","gas_limit":100000,"gas_price":"0x5a00c580","transact_to":"0xf1def7f0e620f39531eb352fe13da6825218e7df","value":"0x0","data":"0x","nonce":3,"chain_id":null,"access_list":[],"gas_priority_fee":null,"blob_hashes":[],"max_fee_per_blob_gas":null,"authorization_list":null},{"caller":"0xa6e796d6f4a76c57cd4dc33218685473d36a1961","gas_limit":42000,"gas_price":"0x4a817c800","transact_to":"0x3f5ce5fbfe3e9af3971dd833d26ba9b5c936f0be","value":"0x48a839098cec800","data":"0x","nonce":2,"chain_id":1,"access_list":[],"gas_priority_fee":null,"blob_hashes":[],"max_fee_per_blob_gas":null,"authorization_list":null},{"caller":"0x6f1632625af590439b8b16e55fcad6136d2c0140","gas_limit":21000,"gas_price":"0x6fc23ac00","transact_to":"0x97e12bd75bdee72d4975d6df410d2d145b3d8457","value":"0x6ee1e5e857ca000","data":"0x","nonce":3,"chain_id":1,"access_list":[],"gas_priority_fee":null,"blob_hashes":[],"max_fee_per_blob_gas":null,"authorization_list":null}]